notnews/__init__.py
notnews/classifiers.py
notnews/cli.py
notnews/data/README.rst
notnews/data/uk_model/url_uk_classifier.joblib
notnews/data/uk_model/url_uk_vectorizer.joblib
notnews/data/us_model/nyt_us_classifier.joblib
notnews/data/us_model/nyt_us_soft_news_classifier.joblib
notnews/data/us_model/nyt_us_soft_news_vectorizer.joblib
notnews/data/us_model/nyt_us_vectorizer.joblib
notnews/llm.py
notnews/utils.py
notnews-0.3.0.dist-info/WHEEL
notnews-0.3.0.dist-info/entry_points.txt
notnews-0.3.0.dist-info/METADATA
notnews-0.3.0.dist-info/RECORD
