Metadata-Version: 2.3
Name: notnews
Version: 0.3.0
Summary: Predict Soft News
Keywords: soft news,classification,machine learning
Author: Suriyan Laohaprapanon, Gaurav Sood
Author-email: Suriyan Laohaprapanon <suriyant@gmail.com>, Gaurav Sood <gsood07@gmail.com>
License: MIT
Classifier: Development Status :: 4 - Beta
Classifier: Intended Audience :: Developers
Classifier: Programming Language :: Python :: 3
Classifier: Programming Language :: Python :: 3.11
Classifier: Programming Language :: Python :: 3.12
Classifier: Programming Language :: Python :: 3.13
Classifier: Topic :: Scientific/Engineering :: Information Analysis
Classifier: Topic :: Software Development :: Libraries :: Python Modules
Classifier: Topic :: Utilities
Requires-Dist: numpy>=1.22.0,<2.0.0
Requires-Dist: pandas>=1.3.0
Requires-Dist: scikit-learn>=1.6.0,<1.8.0
Requires-Dist: joblib
Requires-Dist: tqdm
Requires-Dist: nltk
Requires-Dist: requests
Requires-Dist: beautifulsoup4>=4.11.0
Requires-Dist: click>=8.0.0
Requires-Dist: sphinx>=7.0 ; extra == 'docs'
Requires-Dist: furo>=2024.1.29 ; extra == 'docs'
Requires-Dist: sphinx-autodoc-typehints>=1.25 ; extra == 'docs'
Requires-Dist: sphinx-copybutton>=0.5 ; extra == 'docs'
Requires-Dist: myst-parser>=2.0 ; extra == 'docs'
Requires-Dist: anthropic>=0.18.0 ; extra == 'llm'
Requires-Dist: openai>=1.12.0 ; extra == 'llm'
Requires-Python: >=3.11, <3.14
Project-URL: Bug Tracker, https://github.com/notnews/notnews/issues
Project-URL: Documentation, https://notnews.github.io/notnews/
Project-URL: Homepage, https://github.com/notnews/notnews
Project-URL: Repository, https://github.com/notnews/notnews
Provides-Extra: docs
Provides-Extra: llm
